README.rst
setup.cfg
setup.py
EFGs/__init__.py
EFGs/ifg.py
EFGs/three_level_frag.py
EFGs.egg-info/PKG-INFO
EFGs.egg-info/SOURCES.txt
EFGs.egg-info/dependency_links.txt
EFGs.egg-info/top_level.txt