Metadata-Version: 1.1
Name: EFGs
Version: 0.8.4
Summary: Extended Functional Groups
Home-page: https://github.com/HelloJocelynLu/EFGs
Author: Jocelyn Lu
Author-email: jl8570@nyu.edu
License: MIT
Platform: UNKNOWN
Classifier: Development Status :: 2 - Pre-Alpha
Classifier: License :: OSI Approved :: MIT License
Classifier: Programming Language :: Python :: 3.7
